django_infra/__init__.py
django_infra/api/filters.py
django_infra/api/meta.py
django_infra/api/partial_response.py
django_infra/api/views.py
django_infra/db/bulk_ops.py
django_infra/db/config.py
django_infra/db/enum.py
django_infra/db/models.py
django_infra/env/__init__.py
django_infra/env/shell.py
django_infra/exporter/README.md
django_infra/exporter/__init__.py
django_infra/exporter/admin.py
django_infra/exporter/apps.py
django_infra/exporter/export.py
django_infra/exporter/migrations/0001_initial.py
django_infra/exporter/migrations/0002_alter_queryexport_state.py
django_infra/exporter/migrations/__init__.py
django_infra/exporter/models.py
django_infra/exporter/urls.py
django_infra/exporter/views.py
django_infra/feature_flags/README.md
django_infra/feature_flags/__init__.py
django_infra/feature_flags/admin.py
django_infra/feature_flags/apps.py
django_infra/feature_flags/flags.py
django_infra/feature_flags/middleware.py
django_infra/feature_flags/migrations/0001_initial.py
django_infra/feature_flags/migrations/__init__.py
django_infra/feature_flags/models.py
django_infra/feature_flags/receivers.py
django_infra/feature_flags/serializers.py
django_infra/feature_flags/urls.py
django_infra/feature_flags/views.py
django_infra/testing/__init__.py
django_infra/testing/common.py
django_infra/testing/wrappers.py
django_infra-0.1.11.dist-info/METADATA
django_infra-0.1.11.dist-info/WHEEL
django_infra-0.1.11.dist-info/RECORD
