Metadata-Version: 2.3
Name: django-infra
Version: 0.1.11
Summary: A infra for Django engineers.
Author: Octavio
Author-email: mail@octavio.sh
Requires-Python: >=3.11
Classifier: Programming Language :: Python :: 3
Classifier: Programming Language :: Python :: 3.11
Classifier: Programming Language :: Python :: 3.12
Classifier: Programming Language :: Python :: 3.13
Requires-Dist: django-filter (>=25.1,<26.0)
Requires-Dist: djangorestframework (>=3.15.2,<4.0.0)
Requires-Dist: djangorestframework-camel-case (>=1.4.2,<2.0.0)
Requires-Dist: drf-partial-response (>=0.1.5,<0.2.0)
Requires-Dist: drf-spectacular (>=0.28.0,<0.29.0)
Requires-Dist: pydantic (>=2.10.6,<3.0.0)
